hbp_validation_framework/__init__.py
hbp_validation_framework/datastores.py
hbp_validation_framework/sample.py
hbp_validation_framework/utils.py
hbp_validation_framework/versioning.py
hbp_validation_framework/jsonTreeViewer/CHANGELOG.md
hbp_validation_framework/jsonTreeViewer/LICENSE
hbp_validation_framework/jsonTreeViewer/README.md
hbp_validation_framework/jsonTreeViewer/document.json
hbp_validation_framework/jsonTreeViewer/favicon.ico
hbp_validation_framework/jsonTreeViewer/index.htm
hbp_validation_framework/jsonTreeViewer/jsonTreeViewer.js
hbp_validation_framework/jsonTreeViewer/libs/app/App.js
hbp_validation_framework/jsonTreeViewer/libs/app/README.md
hbp_validation_framework/jsonTreeViewer/libs/app/app.css
hbp_validation_framework/jsonTreeViewer/libs/app/reset.css
hbp_validation_framework/jsonTreeViewer/libs/app/docs/index.htm
hbp_validation_framework/jsonTreeViewer/libs/app/docs/main.css
hbp_validation_framework/jsonTreeViewer/libs/jsonTree/icons.svg
hbp_validation_framework/jsonTreeViewer/libs/jsonTree/jsonTree.css
hbp_validation_framework/jsonTreeViewer/libs/jsonTree/jsonTree.js
hbp_validation_framework/templates/report_template.html
hbp_validation_framework-0.7.1.dist-info/LICENSE.txt
hbp_validation_framework-0.7.1.dist-info/METADATA
hbp_validation_framework-0.7.1.dist-info/WHEEL
hbp_validation_framework-0.7.1.dist-info/top_level.txt
hbp_validation_framework-0.7.1.dist-info/RECORD
